{
    "games" : [
        {
            "id" : 1,
            "title" : "Valorant",
            "release" : 2020,
            "pc" : true,
            "console" : false,
            "image" : "./assets/valorantFrontPage.webp",
            "likes" : 0,
            "comments" : "",
            "description" : "Valorant is a tactical first-person shooter (FPS) game developed by Riot Games. In this team-based multiplayer game, two teams of five players compete in rounds, taking on the roles of Attackers and Defenders. Players choose unique Agents with special abilities, adding strategic depth to the intense gunplay. Valorant emphasizes precise shooting, teamwork, and map control, making it a popular choice for competitive esports play. With a vibrant esports scene and regular updates, Valorant continues to captivate players with its combination of strategy and skill.",
            "time" : "Infinite"
        },
        {
            "id" : 2,
            "title" : "Legend Of Zelda: Tears of The Kingdom",
            "release" : 2023,
            "pc" : false,
            "console" : true,
            "image" : "./assets/TOTK.jpg",
            "likes" : 0,
            "comments" : "",
            "description" : "Link and Zelda set out to explore a cavern beneath Hyrule Castle, from which gloom, a poisonous substance, has been seeping out and causing people to fall ill.",
            "time" : "59"
        },
        {
            "id" : 3,
            "title" : "Overwatch 2",
            "release" : 2022,
            "pc" : true,
            "console" : true,
            "image" : "./assets/Overwatch2.avif",
            "likes" : 0,
            "comments" : "",
            "description" : "Overwatch 2 is a team-based first-person shooter developed by Blizzard Entertainment. Building upon the success of the original Overwatch, it introduces a variety of new features. Players can expect new maps, heroes, and game modes, as well as updated graphics and engine enhancements. Overwatch 2 continues to emphasize team coordination and hero-based gameplay, making it a highly anticipated sequel for fans of the franchise. ",
            "time" : "Infinity"
        },
        {
            "id" : 4,
            "title" : "Stardew Valley",
            "release" : 2016,
            "pc" : true,
            "console" : true,
            "image" : "./assets/StarDew-Valley.jpg",
            "likes" : 0,
            "comments" : "",
            "description" : "",
            "time" : "52"
        },
        {
            "id" : 5,
            "title" : "Super Smash Bros. Ultimate",
            "release" : 2018,
            "pc" : false,
            "console" : true,
            "image" : "./assets/SmashBrosUltimate.webp",
            "likes" : 0,
            "comments" : "",
            "description" : "",
            "time" : "24 to infinite"
        },
        {
            "id" : 6,
            "title" : "Red Dead Redemption 2",
            "release" : 2018,
            "pc" : true,
            "console" : true,
            "image" : "./assets/RedDeadRedemp2.jpg",
            "likes" : 0,
            "comments" : "",
            "description" : "",
            "time" : "50"
        },
        {
            "id" : 7,
            "title" : "GTA: San Andreas",
            "release" : 2004,
            "pc" : true,
            "console" : true,
            "image" : "./assets/GTASanAndreas.jpg",
            "likes" : 0,
            "comments" : "",
            "description" : "",
            "time" : "30"
        },
        {
            "id" : 8,
            "title" : "Super Mario Oddyssey",
            "release" : 2017,
            "pc" : false,
            "console" : true,
            "image" : "./assets/SuperMarioOdyssey.jpeg",
            "likes" : 0,
            "comments" : "",
            "description" : "",
            "time" : "13"
        },
        {
            "id" : 9,
            "title" : "Resident Evil 4 Remake",
            "release" : 2023,
            "pc" : true,
            "console" : true,
            "image" : "./assets/ResidentEvil4.jpg",
            "likes" : 0,
            "comments" : "",
            "description" : "16",
            "time" : 0
        },
        {
            "id" : 10,
            "title" : "Monster Hunter",
            "release" : 2004,
            "pc" : true,
            "console" : true,
            "image" : "./assets/MonsterHunter.jpg",
            "likes" : 0,
            "comments" : "",
            "description" : "",
            "time" : "50"
        }
    ]
}